{"description":"WebTable Assertion|WebTable Assertion","passed":true,"pending":false,"os":"Windows","instanceId":11708,"browser":{"name":"chrome","version":"89.0.4389.128"},"message":"Passed.","trace":"","browserLogs":[{"level":"SEVERE","message":"https://www.globalsqa.com/wp-content/cache/minify/72cc3.default.include.306296.js 0:0 Uncaught ReferenceError: jQuery is not defined","timestamp":1618396778078,"type":""},{"level":"SEVERE","message":"https://pagead2.googlesyndication.com/pagead/js/adsbygoogle.js 66:977 Uncaught P: adsbygoogle.push() error: Only one 'enable_page_level_ads' allowed per page.","timestamp":1618396778171,"type":""}],"screenShotFile":"images\\006e0076-00ef-00a1-0067-009f00da0097.png","timestamp":1618396778023,"duration":2022}
