{"description":"Customers Deposit Functionality_check|XYZ_Bank_Customers_Functionalitycheck","passed":true,"pending":false,"os":"Windows","instanceId":8620,"browser":{"name":"chrome","version":"89.0.4389.128"},"message":"Passed","browserLogs":[{"level":"SEVERE","message":"https://www.globalsqa.com/wp-content/cache/minify/72cc3.default.include.306296.js 0:0 Uncaught ReferenceError: jQuery is not defined","timestamp":1618394018745,"type":""},{"level":"SEVERE","message":"https://pagead2.googlesyndication.com/pagead/js/adsbygoogle.js 66:977 Uncaught P: adsbygoogle.push() error: Only one 'enable_page_level_ads' allowed per page.","timestamp":1618394018799,"type":""}],"screenShotFile":"images\\00d20030-00c7-008b-00b3-00fc00080083.png","timestamp":1618394018368,"duration":1495}
